clue_script
