Metadata-Version: 1.0
Name: clue-script
Version: 0.3.1
Summary: Easy utils for creating a script runner
Home-page: https://github.com/clueproject/clue_script
Author: Rocky Burt
Author-email: rocky@serverzen.com
License: BSD
Keywords: web
Platform: UNKNOWN
Classifier: License :: OSI Approved :: BSD License
Classifier: Programming Language :: Python
Classifier: Topic :: Internet :: WWW/HTTP :: WSGI
